[
  {
    "type": "Threshold",
    "meta": {
      "name": "my-threshold-param"
    },
    "metric": {
      "type": "Node",
      "name": "river-1"
    },
    "threshold": {
      "type": "Literal",
      "value": 5.0
    },
    "predicate": "LT"
  },
  {
    "type": "IndexedArray",
    "meta": {
      "name": "my-indexed-array-param"
    },
    "index_parameter": {
      "type": "Parameter",
      "name": "my-threshold-param"
    },
    "metrics": [
      {
        "type": "Literal",
        "value": 1.5
      },
      {
        "type": "Literal",
        "value": 0.5
      }
    ]
  }
]